galaxy_datasets/__init__.py
galaxy_datasets/check_internal_urls.py
galaxy_datasets/transforms.py
galaxy_datasets/transforms_albumentations.py
galaxy_datasets/transforms_astroalbumentations.py
galaxy_datasets/transforms_custom_torchvision.py
galaxy_datasets/pytorch/__init__.py
galaxy_datasets/pytorch/dataset_utils.py
galaxy_datasets/pytorch/galaxy_datamodule.py
galaxy_datasets/pytorch/galaxy_dataset.py
galaxy_datasets/pytorch/our_datasets.py
galaxy_datasets/pytorch/webdatamodule.py
galaxy_datasets/pytorch/webdataset_utils.py
galaxy_datasets/shared/__init__.py
galaxy_datasets/shared/demo_gz_candels.py
galaxy_datasets/shared/demo_rings.py
galaxy_datasets/shared/desi_low_z.py
galaxy_datasets/shared/download_utils.py
galaxy_datasets/shared/galaxy_mnist.py
galaxy_datasets/shared/gz2.py
galaxy_datasets/shared/gz_candels.py
galaxy_datasets/shared/gz_decals_5.py
galaxy_datasets/shared/gz_desi.py
galaxy_datasets/shared/gz_euclid.py
galaxy_datasets/shared/gz_h2o.py
galaxy_datasets/shared/gz_hubble.py
galaxy_datasets/shared/gz_hubble_euclidized.py
galaxy_datasets/shared/gz_jwst.py
galaxy_datasets/shared/gz_rings.py
galaxy_datasets/shared/gz_ukidss.py
galaxy_datasets/shared/label_metadata.py
galaxy_datasets/shared/tidal.py
galaxy_datasets/shared/torchvision_utils.py
galaxy_datasets/tensorflow/__init__.py
galaxy_datasets/tensorflow/datasets.py
galaxy_datasets-0.0.25.dist-info/licenses/LICENSE
galaxy_datasets-0.0.25.dist-info/METADATA
galaxy_datasets-0.0.25.dist-info/WHEEL
galaxy_datasets-0.0.25.dist-info/top_level.txt
galaxy_datasets-0.0.25.dist-info/RECORD
