Metadata-Version: 2.4
Name: galaxy-datasets
Version: 0.0.25
Summary: Galaxy Zoo datasets for PyTorch/TensorFlow
Home-page: https://github.com/mwalmsley/galaxy-datasets
Author: Mike Walmsley
Author-email: walmsleymk1@gmail.com
Classifier: Programming Language :: Python :: 3
Classifier: License :: OSI Approved :: GNU General Public License (GPL)
Classifier: Operating System :: OS Independent
Classifier: Development Status :: 4 - Beta
Classifier: Environment :: GPU :: NVIDIA CUDA
Requires-Python: >=3.9
License-File: LICENSE
Requires-Dist: numpy
Requires-Dist: pandas
Requires-Dist: pyarrow
Requires-Dist: requests
Requires-Dist: scikit-learn
Requires-Dist: omegaconf
Requires-Dist: datasets>=3.6
Requires-Dist: torch>=1.10.1
Requires-Dist: torchvision>=0.11.2
Requires-Dist: torchaudio>=0.10.1
Requires-Dist: pytorch-lightning>=2.0
Dynamic: author
Dynamic: author-email
Dynamic: classifier
Dynamic: description
Dynamic: description-content-type
Dynamic: home-page
Dynamic: license-file
Dynamic: requires-dist
Dynamic: requires-python
Dynamic: summary
